slack2python/__init__.py
slack2python/channel.py
slack2python/client.py
slack2python/member.py
slack2python/message.py
slack2python/util.py
slack2python-0.1.3.dist-info/METADATA
slack2python-0.1.3.dist-info/LICENSE
slack2python-0.1.3.dist-info/WHEEL
slack2python-0.1.3.dist-info/RECORD
